{
  "publicPath": "/_nuxt/",
  "all": [
    "../server/index.spa.html",
    "../server/index.ssr.html",
    "0a6e9910774ef717de81.js",
    "0acf8288adebac6d2c2e.js",
    "16ba5fb580dcc8318606.js",
    "30c62b7219acf71b6551.js",
    "556c537cd503202a3c10.js",
    "7fd00e86852c4e317527.js",
    "982c6223f41c494eb0b0.js",
    "LICENSES",
    "bd9b23736bf68241170cdd97d6e7f54d.jpg",
    "c21d2abf80649d180d1a.js",
    "cb52122f4c854c3bd1c9.js",
    "ccb9a6be7987d7699a30.js",
    "d4aaee4728581403e399.js",
    "df2c14d965473b6e1161.js",
    "e2f362137e3e97167601ae5d4fd941df.jpg",
    "ece511fe3fffdffc01f3.js"
  ],
  "initial": [
    "0acf8288adebac6d2c2e.js",
    "c21d2abf80649d180d1a.js",
    "d4aaee4728581403e399.js"
  ],
  "async": [
    "0a6e9910774ef717de81.js",
    "16ba5fb580dcc8318606.js",
    "30c62b7219acf71b6551.js",
    "556c537cd503202a3c10.js",
    "7fd00e86852c4e317527.js",
    "982c6223f41c494eb0b0.js",
    "cb52122f4c854c3bd1c9.js",
    "ccb9a6be7987d7699a30.js",
    "df2c14d965473b6e1161.js",
    "ece511fe3fffdffc01f3.js"
  ],
  "modules": {
    "17335832": [
      11
    ],
    "41025702": [
      11
    ],
    "47192160": [
      11
    ],
    "48130036": [
      11
    ],
    "70406192": [
      2
    ],
    "73437864": [
      11
    ],
    "46311e6f": [
      11
    ],
    "67b4d560": [
      11
    ],
    "15851b0c": [
      11
    ],
    "2cae8543": [
      14,
      16
    ],
    "e9a34694": [
      11
    ],
    "a036dff8": [
      11
    ],
    "71d6b09c": [
      11
    ],
    "3a0d74ee": [
      14,
      16
    ],
    "6a6a0290": [
      11
    ],
    "73e45aeb": [
      11
    ],
    "5b3ba430": [
      11
    ],
    "ff61872a": [
      11
    ],
    "df22a966": [
      11
    ],
    "547f929a": [
      11
    ],
    "5f98abb5": [
      11
    ],
    "118c1612": [
      14,
      16
    ],
    "6cb095b6": [
      14,
      16
    ],
    "2356d69e": [
      11
    ],
    "7d920f90": [
      11
    ],
    "c52445c0": [
      11
    ],
    "ca2aaec6": [
      11
    ],
    "9c000e16": [
      11
    ],
    "377e2352": [
      11
    ],
    "15e1fa39": [
      14,
      16
    ],
    "80edd1b4": [
      11
    ],
    "ab91c3d6": [
      11
    ],
    "4e26112c": [
      11
    ],
    "aaf47b70": [
      11
    ],
    "3fc6e6cd": [
      11
    ],
    "38113fc9": [
      11
    ],
    "7cd3afd2": [
      11
    ],
    "26b0709a": [
      11
    ],
    "4be90998": [
      11
    ],
    "6ece3902": [
      11
    ],
    "0d31efea": [
      11
    ],
    "dd040944": [
      11
    ],
    "1e83fa0e": [
      11
    ],
    "2ec28432": [
      11
    ],
    "d9cd5d7a": [
      11
    ],
    "2f5d23a6": [
      11
    ],
    "071b8ecc": [
      11
    ],
    "0efd0cdb": [
      11
    ],
    "6a95052c": [
      11
    ],
    "b0a7273e": [
      11
    ],
    "10b152c5": [
      11
    ],
    "5579d07c": [
      11
    ],
    "e7123830": [
      11
    ],
    "d421eef4": [
      11
    ],
    "1569bf16": [
      11
    ],
    "0f71952f": [
      11
    ],
    "0ca9d8b8": [
      14,
      16
    ],
    "35b2886d": [
      14,
      16
    ],
    "340cd7ea": [
      14,
      16
    ],
    "1cd651e2": [
      14,
      16
    ],
    "e6274a14": [
      14,
      16
    ],
    "7290d781": [
      14,
      16
    ],
    "97db64a6": [
      14,
      16
    ],
    "f6c17b9e": [
      14,
      16
    ],
    "24dce825": [
      11
    ],
    "27d3ae2c": [
      11
    ],
    "7cbd569b": [
      11
    ],
    "776a5c50": [
      11
    ],
    "54d4b832": [
      11
    ],
    "5d516ac8": [
      11
    ],
    "d9635794": [
      11
    ],
    "7cbf9c76": [
      11
    ],
    "79d35dea": [
      11
    ],
    "685ca404": [
      11
    ],
    "2865a3c0": [
      11
    ],
    "34ae86da": [
      11
    ],
    "63d052cb": [
      11
    ],
    "3cf5c1d6": [
      11
    ],
    "4c08fd7c": [
      11
    ],
    "315a2d7a": [
      11
    ],
    "5d9bd446": [
      11
    ],
    "c704d6ca": [
      11
    ],
    "4eb6859b": [
      11
    ],
    "2b0d7f85": [
      11
    ],
    "2e08a1fe": [
      11
    ],
    "5dd0e776": [
      11
    ],
    "7cb8cae5": [
      11
    ],
    "d122220e": [
      11
    ],
    "9eb6e400": [
      11
    ],
    "0e1f59bf": [
      11
    ],
    "7181df48": [
      11
    ],
    "5bf9d892": [
      11
    ],
    "38c4a100": [
      11
    ],
    "a39c0cd8": [
      11
    ],
    "66a78356": [
      11
    ],
    "2cc7e17c": [
      11
    ],
    "1d8e3969": [
      11
    ],
    "6177124c": [
      11
    ],
    "0bda2e0a": [
      11
    ],
    "547160e1": [
      11
    ],
    "3ce83af2": [
      11
    ],
    "08e4c57a": [
      11
    ],
    "709ced68": [
      11
    ],
    "30591f56": [
      11
    ],
    "58ff555e": [
      11
    ],
    "c994f81c": [
      11
    ],
    "66a66974": [
      11
    ],
    "1ad1bcd6": [
      11
    ],
    "5e4f75b1": [
      11
    ],
    "6291f1b0": [
      11
    ],
    "63365e52": [
      11
    ],
    "464756ce": [
      14,
      16
    ],
    "3040dfda": [
      11
    ],
    "8f8af63a": [
      14,
      16
    ],
    "1e054178": [
      11
    ],
    "5ef26ff6": [
      14,
      16
    ],
    "e34d0d2e": [
      14,
      16
    ],
    "45ad5c71": [
      11
    ],
    "7e11bede": [
      11
    ],
    "d8c972b4": [
      11
    ],
    "902322fe": [
      11
    ],
    "ce9001f2": [
      11
    ],
    "c513d60c": [
      11
    ],
    "6c65e6e2": [
      11
    ],
    "5db80547": [
      11
    ],
    "495900ee": [
      11
    ],
    "a7418b6a": [
      11
    ],
    "01fac372": [
      11
    ],
    "6a918aee": [
      11
    ],
    "49805b7a": [
      11
    ],
    "5a3a2fe4": [
      11
    ],
    "57ef4efc": [
      11
    ],
    "e568fa40": [
      11
    ],
    "08973bd4": [
      11
    ],
    "19b378b2": [
      11
    ],
    "740904e6": [
      11
    ],
    "7545eece": [
      11
    ],
    "2e5975bc": [
      11
    ],
    "e193ae46": [
      11
    ],
    "2961f852": [
      11
    ],
    "9481bd9a": [
      11
    ],
    "137b3eb6": [
      14,
      16
    ],
    "5d2debc5": [
      11
    ],
    "fff32aa8": [
      11
    ],
    "27dbb4d0": [
      11
    ],
    "4bee4b4c": [
      11
    ],
    "6f3e0c30": [
      11
    ],
    "6727d187": [
      11
    ],
    "9f4f14d6": [
      11
    ],
    "b1d1ac1c": [
      11
    ],
    "060cfe77": [
      11
    ],
    "5aa1a995": [
      11
    ],
    "65c8a69b": [
      11
    ],
    "3a6a2c2f": [
      11
    ],
    "01b658f0": [
      14,
      16
    ],
    "9aa989a8": [
      14,
      16
    ],
    "40c25a51": [
      14,
      16
    ],
    "95db852e": [
      14,
      16
    ],
    "ce5f7ff0": [
      14,
      16
    ],
    "9b14e49c": [
      14,
      16
    ],
    "d4c163ea": [
      14,
      16
    ],
    "5cefe05e": [
      14,
      16
    ],
    "832e35fa": [
      14,
      16
    ],
    "57ddb824": [
      14,
      16
    ],
    "1c0c422e": [
      14,
      16
    ],
    "c403ce6e": [
      14,
      16
    ],
    "051f8f6f": [
      14,
      16
    ],
    "7cf32b52": [
      14,
      16
    ],
    "69bc3c6a": [
      14,
      16
    ],
    "84731d62": [
      14,
      16
    ],
    "8e2a4216": [
      14,
      16
    ],
    "3d53cd4c": [
      14,
      16
    ],
    "b0df588e": [
      14,
      16
    ],
    "7537e3b4": [
      14,
      16
    ],
    "a05c50b6": [
      14,
      16
    ],
    "149dc18a": [
      14,
      16
    ],
    "70707c5c": [
      11
    ],
    "e8205a5e": [
      11
    ],
    "0f308e44": [
      11
    ],
    "f61f078c": [
      11
    ],
    "2ffbc443": [
      14,
      16
    ],
    "a4d61456": [
      14,
      16
    ],
    "1167564b": [
      11
    ],
    "6e0dcc07": [
      11
    ],
    "079ebbf4": [
      11
    ],
    "3d156134": [
      11
    ],
    "488436d7": [
      11
    ],
    "d1498a3c": [
      11
    ],
    "60a7d670": [
      11
    ],
    "afbd058c": [
      11
    ],
    "2697a248": [
      11
    ],
    "8f5ee2ae": [
      11
    ],
    "54c11070": [
      11
    ],
    "36297d27": [
      11
    ],
    "7157611d": [
      11
    ],
    "27e16428": [
      11
    ],
    "e3ee5bfa": [
      11
    ],
    "22c8a853": [
      14,
      16
    ],
    "6a80d179": [
      14,
      16
    ],
    "3fac45a0": [
      14,
      16
    ],
    "7eb82b90": [
      14,
      16
    ],
    "e1462d8c": [
      14,
      16
    ],
    "c0cc8af0": [
      14,
      16
    ],
    "fd5d9f42": [
      13
    ],
    "1c722b86": [
      6
    ],
    "51d960d8": [
      5
    ],
    "78e81db0": [
      2
    ],
    "71cb4bb8": [
      7
    ],
    "64b8c1d6": [
      17
    ],
    "558fa978": [
      8
    ],
    "4cf091e8": [
      4
    ],
    "96a6c0fc": [
      15
    ],
    "0a2f843e": [
      15
    ],
    "68928efe": [
      15
    ],
    "1c711637": [
      12,
      10
    ],
    "d8688148": [
      12,
      10
    ],
    "0d9c9af3": [
      12,
      10
    ],
    "44de2516": [
      12,
      10
    ],
    "70e76acd": [
      12,
      10
    ],
    "10c99b86": [
      12,
      10
    ],
    "388c026b": [
      13
    ],
    "5674bd66": [
      13
    ],
    "1f7eaadc": [
      6
    ],
    "36e692cd": [
      6
    ],
    "0732bf08": [
      5
    ],
    "b33d3926": [
      5
    ],
    "d9d9ec88": [
      2
    ],
    "e8139078": [
      7
    ],
    "7e7a0582": [
      7
    ],
    "388740e2": [
      17
    ],
    "7f2d291d": [
      17
    ],
    "2139d160": [
      8
    ],
    "242fdccb": [
      8
    ],
    "026abf80": [
      4
    ],
    "63e3c425": [
      4
    ],
    "7e312720": [
      4
    ],
    "782453b8": [
      4
    ],
    "dd06fe14": [
      15
    ],
    "34f2944a": [
      15
    ],
    "8fd6ea26": [
      15
    ],
    "355e1ab0": [
      15
    ],
    "d875b71c": [
      15
    ],
    "0edde352": [
      15
    ],
    "45541eab": [
      12,
      10
    ],
    "b265b960": [
      12,
      10
    ],
    "86a27060": [
      12,
      10
    ],
    "1e27cc75": [
      12,
      10
    ],
    "017dfaec": [
      12,
      10
    ],
    "5d5afb6c": [
      12,
      10
    ],
    "42e2eb55": [
      12,
      10
    ],
    "06a594b1": [
      12,
      10
    ],
    "9c4bc292": [
      12,
      10
    ],
    "2d3c7fff": [
      12,
      10
    ],
    "d304848c": [
      12,
      10
    ],
    "7010ba8a": [
      12,
      10
    ],
    "5646b722": [
      12,
      10
    ],
    "a7f0f84e": [
      12,
      10
    ],
    "3e8e52d8": [
      12,
      10
    ],
    "27baa1b1": [
      12,
      10
    ],
    "722d73d4": [
      12,
      10
    ],
    "176e6ec4": [
      12,
      10
    ],
    "117e9dc2": [
      15
    ],
    "5fdb9793": [
      8
    ],
    "1e88ceee": [
      13
    ],
    "5c6af865": [
      17
    ],
    "2b571507": [
      7
    ],
    "9a243602": [
      2
    ],
    "1bd463d6": [
      6
    ],
    "10869a6d": [
      4
    ],
    "841f2896": [
      5
    ]
  },
  "assetsMapping": {
    "0a6e9910774ef717de81.js": "22290dfc",
    "0acf8288adebac6d2c2e.js": "6fca0322",
    "16ba5fb580dcc8318606.js": "249c1620",
    "30c62b7219acf71b6551.js": "29bd80b0",
    "556c537cd503202a3c10.js": "6ecbf352",
    "7fd00e86852c4e317527.js": "9f08fbf8",
    "982c6223f41c494eb0b0.js": "7141aae0",
    "c21d2abf80649d180d1a.js": "0859c165",
    "cb52122f4c854c3bd1c9.js": "2a130dde",
    "ccb9a6be7987d7699a30.js": "b70ccc2a",
    "d4aaee4728581403e399.js": "1a3ae26b",
    "df2c14d965473b6e1161.js": "1a53cc92",
    "ece511fe3fffdffc01f3.js": "ef1a74bc"
  }
}